closeio/__init__.py
closeio/closeio.py
closeio/exceptions.py
closeio/utils.py
closeio/contrib/__init__.py
closeio/contrib/pytest_plugin.py
closeio/contrib/testing_stub.py
closeio/contrib/django/__init__.py
closeio/contrib/django/signals.py
closeio/contrib/django/urls.py
closeio/contrib/django/utils.py
closeio/contrib/django/views.py
faster_closeio-1.5.2.dist-info/AUTHORS
faster_closeio-1.5.2.dist-info/LICENSE
faster_closeio-1.5.2.dist-info/METADATA
faster_closeio-1.5.2.dist-info/WHEEL
faster_closeio-1.5.2.dist-info/entry_points.txt
faster_closeio-1.5.2.dist-info/pbr.json
faster_closeio-1.5.2.dist-info/top_level.txt
faster_closeio-1.5.2.dist-info/RECORD
