Metadata-Version: 2.1
Name: faster-closeio
Version: 1.5.2
Summary: Slim API wrapper to access close.io CRM.
Home-page: https://github.com/Thermondo/closeio
Author: Thermondo GmbH
Author-email: opensource@thermondo.de
License: Apache-2
Platform: UNKNOWN
Classifier: Development Status :: 7 - Inactive
Classifier: Environment :: Web Environment
Classifier: Intended Audience :: Developers
Classifier: License :: OSI Approved :: Apache Software License
Classifier: Operating System :: OS Independent
Classifier: Programming Language :: Python :: 3
Classifier: Framework :: Django
Requires-Dist: python-dateutil (>=2.2)
Requires-Dist: requests (>=2.2.1)
Requires-Dist: six (>=1.6.1)
Requires-Dist: slumber (==0.7.1)
Provides-Extra: django
Requires-Dist: django (>=1.11) ; extra == 'django'
